endurance_etl/__init__.py
endurance_etl-0.1.0.dist-info/LICENSE
endurance_etl-0.1.0.dist-info/METADATA
endurance_etl-0.1.0.dist-info/WHEEL
endurance_etl-0.1.0.dist-info/RECORD
