Metadata-Version: 2.1
Name: endurance-etl
Version: 0.1.0
Summary: Polars and duckdb based json configured simple ETL pipelines
License: MIT
Author: Benjamin Gutzmann
Author-email: gutzemann@gmail.com
Requires-Python: >=3.9,<4.0
Classifier: License :: OSI Approved :: MIT License
Classifier: Programming Language :: Python :: 3
Classifier: Programming Language :: Python :: 3.9
Classifier: Programming Language :: Python :: 3.10
Classifier: Programming Language :: Python :: 3.11
Requires-Dist: duckdb (>=0.7.1,<0.8.0)
Requires-Dist: polars (>=0.17.3,<0.18.0)
